setup.py
loggingtool/__init__.py
loggingtool/loggingtool.py
loggingtool.egg-info/PKG-INFO
loggingtool.egg-info/SOURCES.txt
loggingtool.egg-info/dependency_links.txt
loggingtool.egg-info/requires.txt
loggingtool.egg-info/top_level.txt