Metadata-Version: 1.0
Name: loggingtool
Version: 18.11.20
Summary: The package for logging
Home-page: https://github.com/lijiacaigit/LogTool
Author: Lijiacai
Author-email: 1050518702@qq.com
License: MIT License
Keywords: pip,logging,loggingtool
Platform: any
